karellen_llvm_lldb-21.1.8.data/data/bin/lldb
karellen_llvm_lldb-21.1.8.data/data/bin/lldb-argdumper
karellen_llvm_lldb-21.1.8.data/data/bin/lldb-dap
karellen_llvm_lldb-21.1.8.data/data/bin/lldb-instr
karellen_llvm_lldb-21.1.8.data/data/bin/lldb-server
karellen_llvm_lldb-21.1.8.data/data/lib/liblldb.so.21.1.8
karellen_llvm_lldb-21.1.8.data/data/lib/liblldbIntelFeatures.so.21.1
karellen_llvm_lldb-21.1.8.data/purelib/karellen_llvm_lldb-21.1.8.pth
karellen_llvm_lldb-21.1.8.data/purelib/lldb/__init__.py
karellen_llvm_lldb-21.1.8.data/purelib/lldb/embedded_interpreter.py
karellen_llvm_lldb-21.1.8.data/purelib/lldb/formatters/Logger.py
karellen_llvm_lldb-21.1.8.data/purelib/lldb/formatters/__init__.py
karellen_llvm_lldb-21.1.8.data/purelib/lldb/formatters/attrib_fromdict.py
karellen_llvm_lldb-21.1.8.data/purelib/lldb/formatters/cache.py
karellen_llvm_lldb-21.1.8.data/purelib/lldb/formatters/metrics.py
karellen_llvm_lldb-21.1.8.data/purelib/lldb/formatters/synth.py
karellen_llvm_lldb-21.1.8.data/purelib/lldb/formatters/cpp/__init__.py
karellen_llvm_lldb-21.1.8.data/purelib/lldb/formatters/cpp/gnu_libstdcpp.py
karellen_llvm_lldb-21.1.8.data/purelib/lldb/formatters/cpp/libcxx.py
karellen_llvm_lldb-21.1.8.data/purelib/lldb/plugins/__init__.py
karellen_llvm_lldb-21.1.8.data/purelib/lldb/plugins/operating_system.py
karellen_llvm_lldb-21.1.8.data/purelib/lldb/plugins/parsed_cmd.py
karellen_llvm_lldb-21.1.8.data/purelib/lldb/plugins/scripted_platform.py
karellen_llvm_lldb-21.1.8.data/purelib/lldb/plugins/scripted_process.py
karellen_llvm_lldb-21.1.8.data/purelib/lldb/plugins/scripted_thread_plan.py
karellen_llvm_lldb-21.1.8.data/purelib/lldb/utils/__init__.py
karellen_llvm_lldb-21.1.8.data/purelib/lldb/utils/in_call_stack.py
karellen_llvm_lldb-21.1.8.data/purelib/lldb/utils/symbolication.py
karellen_llvm_lldb-21.1.8.dist-info/METADATA
karellen_llvm_lldb-21.1.8.dist-info/WHEEL
karellen_llvm_lldb-21.1.8.dist-info/axle.lck
karellen_llvm_lldb-21.1.8.dist-info/namespace_packages.txt
karellen_llvm_lldb-21.1.8.dist-info/require-libpython
karellen_llvm_lldb-21.1.8.dist-info/symlinks.txt
karellen_llvm_lldb-21.1.8.dist-info/top_level.txt
karellen_llvm_lldb-21.1.8.dist-info/RECORD
