Metadata-Version: 2.4
Name: karellen-llvm-lldb
Version: 21.1.8
Summary: Karellen LLDB infrastructure
Home-page: https://github.com/karellen/karellen-llvm
Author: Karellen, Inc.
Author-email: supervisor@karellen.co
Maintainer: Arcadiy Ivanov
Maintainer-email: arcadiy@karellen.co
License: Apache License, Version 2.0
Project-URL: Bug Tracker, https://github.com/karellen/karellen-llvm/issues
Project-URL: Documentation, https://github.com/karellen/karellen-llvm
Project-URL: Source Code, https://github.com/karellen/karellen-llvm
Keywords: LLVM,lldb,debugger
Classifier: Programming Language :: Python
Classifier: Operating System :: POSIX :: Linux
Classifier: Development Status :: 5 - Production/Stable
Classifier: Intended Audience :: Developers
Classifier: License :: OSI Approved :: Apache Software License
Classifier: Topic :: Software Development :: Build Tools
Requires-Dist: karellen-llvm-clang==21.1.8
Requires-Dist: wheel-axle-runtime<1.0,>0.0.5
Dynamic: author
Dynamic: author-email
Dynamic: classifier
Dynamic: description
Dynamic: description-content-type
Dynamic: home-page
Dynamic: keywords
Dynamic: license
Dynamic: maintainer
Dynamic: maintainer-email
Dynamic: project-url
Dynamic: requires-dist
Dynamic: summary
